{
  "id": "n2-reading-024",
  "title": "SNS時代のコミュニケーション",
  "category": "essay",
  "difficulty": 4,
  "questionType": "主張理解・長文",
  "passage": "SNSの普及により、コミュニケーションのあり方が大きく変わった。世界中の人と瞬時につながれる時代になり、情報の共有も容易になった。しかし、この変化は必ずしも良い面ばかりではない。\n\nSNSのメリットは明らかだ。遠く離れた友人や家族と簡単に連絡が取れ、共通の趣味を持つ人々とつながることができる。また、災害時には安否確認の手段としても役立つ。ビジネスでも、SNSを活用したマーケティングが主流となっている。\n\nその一方で、SNSには深刻な問題も存在する。最も懸念されるのは、表面的なつながりが増え、深い人間関係が失われつつあることだ。「いいね」の数を気にするあまり、本当の自分を表現できなくなる人も少なくない。また、他人の投稿と自分を比較し、劣等感を抱く人が増えている。SNS上では、みんなが幸せそうに見えるが、それは現実の一部を切り取ったものに過ぎない。\n\nさらに、匿名性を利用した誹謗中傷も問題となっている。顔が見えないことで、普段なら言わないような厳しい言葉を投げかける人がいる。これにより、精神的に傷つく人が後を絶たない。特に若者への影響は深刻で、SNSでのいじめが社会問題化している。\n\n情報の信頼性も課題だ。SNSでは、真偽不明の情報が瞬く間に拡散される。フェイクニュースに惑わされ、誤った判断をしてしまうこともある。情報を鵜呑みにせず、批判的に考える力が求められている。\n\nでは、SNSとどう向き合えばよいのか。完全に否定するのではなく、賢く利用することが大切だと私は考える。SNSに支配されるのではなく、自分がSNSを使うという意識を持つべきだ。投稿を見る時間を決めたり、定期的にデジタルデトックスをしたりすることも有効だろう。\n\nそして何より、SNS上のつながりだけに頼らず、直接会って話す機会を大切にすることだ。対面でのコミュニケーションでしか得られない温かさや安心感がある。SNSは便利なツールだが、それがすべてではない。バランスを保ちながら、健全な人間関係を築いていくことが重要である。",
  "estimatedTime": 10,
  "questions": [
    {
      "id": "q1",
      "questionText": "SNSの問題として筆者が挙げていないものはどれか。",
      "type": "multiple-choice",
      "choices": [
        {"id": "a", "text": "表面的なつながりが増えること"},
        {"id": "b", "text": "誹謗中傷が起きること"},
        {"id": "c", "text": "情報の信頼性が低いこと"},
        {"id": "d", "text": "インターネットの速度が遅いこと"}
      ],
      "correctAnswer": "d",
      "explanation": "インターネットの速度については言及されていません。他の3つは具体的な問題として挙げられています。",
      "points": 1
    },
    {
      "id": "q2",
      "questionText": "筆者が考える情報への向き合い方として正しいものはどれか。",
      "type": "multiple-choice",
      "choices": [
        {"id": "a", "text": "すべての情報を信じる"},
        {"id": "b", "text": "情報を批判的に考える"},
        {"id": "c", "text": "SNSの情報は見ない"},
        {"id": "d", "text": "情報は必要ない"}
      ],
      "correctAnswer": "b",
      "explanation": "第5段落で「情報を鵜呑みにせず、批判的に考える力が求められている」と述べられています。",
      "points": 1
    },
    {
      "id": "q3",
      "questionText": "筆者が最も伝えたいことは何か。",
      "type": "multiple-choice",
      "choices": [
        {"id": "a", "text": "SNSは完全に悪いものだ"},
        {"id": "b", "text": "SNSだけに頼るのではなく、バランスを保つことが大切だ"},
        {"id": "c", "text": "対面コミュニケーションは不要だ"},
        {"id": "d", "text": "SNSを使う時間を増やすべきだ"}
      ],
      "correctAnswer": "b",
      "explanation": "最後の段落で「バランスを保ちながら、健全な人間関係を築いていくことが重要」と結論づけています。",
      "points": 1
    }
  ],
  "vocabulary": [
    {"kanji": "瞬時", "reading": "しゅんじ", "meaning": "instant, moment"},
    {"kanji": "劣等感", "reading": "れっとうかん", "meaning": "inferiority complex"},
    {"kanji": "誹謗中傷", "reading": "ひぼうちゅうしょう", "meaning": "slander, defamation"},
    {"kanji": "鵜呑み", "reading": "うのみ", "meaning": "swallowing whole, believing uncritically"},
    {"kanji": "健全", "reading": "けんぜん", "meaning": "sound, healthy"},
    {"kanji": "支配", "reading": "しはい", "meaning": "control, domination"}
  ],
  "grammarPoints": ["〜により", "〜つつある", "〜に過ぎない", "〜ではなく", "〜ことが大切だ", "〜ながら"],
  "metadata": {
    "dateAdded": "2025-11-10",
    "source": "Original"
  }
}
